[{"id_message": 25710340627, "message": "En páginas de juegos está", "date": "2020-04-01 15:34:51"}, {"id_message": 92240525425, "message": "Yo ya no se dónde lo jugué", "date": "2020-04-01 15:34:59"}, {"id_message": 8035989448, "message": "Pero esque no puedo cara de por favor", "date": "2020-04-01 15:50:32"}, {"id_message": 57069473121, "message": "Me alegro te haya gustado", "date": "2020-04-01 18:10:09"}, {"id_message": 71067650178, "message": "Yo escucho a esos", "date": "2020-04-01 18:16:26"}, {"id_message": 74060129114, "message": "Un bot asigna los roles", "date": "2020-04-01 18:31:52"}, {"id_message": 32990377192, "message": "Y hace de narrador", "date": "2020-04-01 18:31:55"}, {"id_message": 18727411268, "message": "Y nosotros hablamos entre nosotros en el grupo donde se juega", "date": "2020-04-01 18:32:13"}, {"id_message": 21095367888, "message": "Te meto en el grupo ok ?", "date": "2020-04-01 18:41:42"}, {"id_message": 77596475331, "message": "O una serie de preguntas mejor dicho", "date": "2020-04-01 23:46:59"}, {"id_message": 91238592038, "message": "mano abierta", "date": "2020-04-02 05:03:28"}, {"id_message": 84624206003, "message": "Ma o meno eh", "date": "2020-04-02 17:24:56"}, {"id_message": 59526743385, "message": "Porque lo piensas ? xd", "date": "2020-04-03 04:13:33"}, {"id_message": 5202607301, "message": "Tengo sueño , debería dormir , pero no quiero xd", "date": "2020-04-03 04:13:49"}, {"id_message": 70350705589, "message": "Tengo una pregunta para l @s nuev @s", "date": "2020-04-03 04:19:08"}, {"id_message": 86825984912, "message": "@USER @USER como llegaron aquí ?", "date": "2020-04-03 04:19:28"}, {"id_message": 33709753376, "message": "Solo era eso gracias", "date": "2020-04-03 04:20:42"}, {"id_message": 80282232837, "message": "El creador tambien es argentino", "date": "2020-04-03 04:22:25"}, {"id_message": 63117245956, "message": "Diría que hay más ... Pero no sé", "date": "2020-04-03 04:23:27"}, {"id_message": 94355877660, "message": "No me gustan las grandes aglomeraciones", "date": "2020-04-03 04:23:45"}, {"id_message": 30910958934, "message": "Pero fobia no xd", "date": "2020-04-03 04:24:09"}, {"id_message": 65780388296, "message": "El sabe de estas cosas", "date": "2020-04-03 04:31:31"}, {"id_message": 53704225256, "message": "Pero no queremos problemas", "date": "2020-04-03 04:41:20"}, {"id_message": 2222425685, "message": "Pero sin alterarte , nosotros te escuchamos", "date": "2020-04-03 04:41:58"}, {"id_message": 94195432368, "message": "Y para eso está el grupo", "date": "2020-04-03 04:42:08"}, {"id_message": 23809646152, "message": "Solo ha sido un malentendido", "date": "2020-04-03 04:42:16"}, {"id_message": 18708354767, "message": "Creo que ella se fue", "date": "2020-04-03 04:43:02"}, {"id_message": 16279499381, "message": "Y hablábamos los mismo", "date": "2020-04-03 04:50:37"}, {"id_message": 56726947878, "message": "Tu no tienes sueño ?", "date": "2020-04-03 05:01:20"}, {"id_message": 29007047341, "message": "Clash royale cara llorando de risa cara llorando de risa", "date": "2020-04-03 05:19:47"}, {"id_message": 11553160458, "message": "Estamos ayudando a las autoridades de salud a difundir información precisa sobre la pandemia a través de canales verificados . URL", "date": "2020-04-04 21:53:25"}, {"id_message": 1112136987, "message": "Aburrido por la cuarentena", "date": "2020-04-05 19:18:38"}, {"id_message": 63655372438, "message": "Por eso te querías colar eh ?", "date": "2020-04-05 19:55:03"}, {"id_message": 36601928608, "message": "Pasa foto cuando esté acabado", "date": "2020-04-06 16:34:56"}, {"id_message": 72836686821, "message": "Creo que aún le falta un poco no ?", "date": "2020-04-06 19:11:42"}, {"id_message": 34413474465, "message": "Pero está en acciones recientes", "date": "2020-04-06 23:06:43"}, {"id_message": 71165865272, "message": "Has perreado solo todo el día ?", "date": "2020-04-07 21:59:03"}, {"id_message": 39248033669, "message": "Como el amor de ella", "date": "2020-04-07 21:59:52"}, {"id_message": 33434936762, "message": "Si que estás drogado si", "date": "2020-04-08 00:14:20"}, {"id_message": 92912137085, "message": "Quién es esa ? wtf", "date": "2020-04-08 00:19:18"}, {"id_message": 39599618402, "message": "Alguien tiene Stickers de \" INUYASHA \" ?", "date": "2020-04-08 00:34:08"}, {"id_message": 45420949631, "message": "Ataque a los titanes", "date": "2020-04-08 20:30:58"}, {"id_message": 42777118373, "message": "Es lo mismo pero en Español", "date": "2020-04-08 20:32:03"}, {"id_message": 99050005316, "message": "Que bien ... De dónde eres ? Si se puedes saber xd", "date": "2020-04-09 20:45:50"}, {"id_message": 55104871608, "message": "Yo toy agobiado , demasiada tarea y muy poco tiempo", "date": "2020-04-09 20:46:26"}, {"id_message": 316080769, "message": "Yo de Bcn UwU", "date": "2020-04-09 20:47:03"}, {"id_message": 89134827402, "message": "Es solo que tengo mucho", "date": "2020-04-09 20:47:19"}, {"id_message": 86838699847, "message": "Oye , puedo hacerte una pregunta", "date": "2020-04-09 20:56:03"}, {"id_message": 80041842801, "message": "Cuánto llevas en Telegram", "date": "2020-04-09 20:56:38"}, {"id_message": 87271212218, "message": "Es por una cosa ...", "date": "2020-04-09 20:57:55"}, {"id_message": 32017502841, "message": "Rojas F . J . N . cuanto llevas en telegram ?", "date": "2020-04-09 20:58:32"}, {"id_message": 26810026874, "message": "Su cuenta aún está viva", "date": "2020-04-09 20:58:41"}, {"id_message": 86636355157, "message": "Esque hay una cosa que intento averiguae", "date": "2020-04-09 21:01:25"}, {"id_message": 18074467521, "message": "Y no se con qué está relacionado", "date": "2020-04-09 21:01:31"}, {"id_message": 88214722486, "message": "Y pues voy preguntando", "date": "2020-04-09 21:01:49"}, {"id_message": 39262219086, "message": "No sé qué significa ese \" DC \" ni el número", "date": "2020-04-09 21:03:15"}, {"id_message": 17318775476, "message": "Yo he preguntado por el tiempo que llevas porque creo que está relacionado con ese \" DC \"", "date": "2020-04-09 21:05:29"}, {"id_message": 89121164966, "message": "Y ese César en una persona mala que estuvo aquí", "date": "2020-04-09 21:05:42"}, {"id_message": 68736709105, "message": "Joder Rojas cara llorando de risa cara llorando de risa", "date": "2020-04-09 21:06:01"}, {"id_message": 63566524886, "message": "Perdón por las molestias", "date": "2020-04-09 21:06:42"}, {"id_message": 56720329620, "message": "Pero esque hemos tenido algunos problemillas", "date": "2020-04-09 21:09:29"}, {"id_message": 36500967134, "message": "Y pues ... Espero lo entiendas cara sonriendo con sudor frío", "date": "2020-04-09 21:09:37"}, {"id_message": 43034551858, "message": "El creador y yo", "date": "2020-04-10 00:18:29"}, {"id_message": 22355833562, "message": "Y pues la anclo para quien sepa responder", "date": "2020-04-10 00:19:57"}, {"id_message": 72478292819, "message": "Nop , estoy en más grupos", "date": "2020-04-10 00:20:29"}, {"id_message": 75835554545, "message": "Y estoy en algunos con admin compartido", "date": "2020-04-10 00:25:25"}, {"id_message": 70183882355, "message": "Solo tiene un subscriptor y yo xx", "date": "2020-04-10 00:26:38"}, {"id_message": 50679479373, "message": "Te he metido en el canal cara llorando de risa cara llorando de risa", "date": "2020-04-10 00:26:55"}, {"id_message": 31601869496, "message": "No , solo que no está mucho por Telegram xd", "date": "2020-04-10 00:31:29"}, {"id_message": 22663101882, "message": "Hola de nuevo xz", "date": "2020-04-12 12:01:55"}, {"id_message": 52910891092, "message": "He tenido días mejores", "date": "2020-04-12 20:40:43"}, {"id_message": 24045522977, "message": "No confundas tus sentimientos con los míos", "date": "2020-04-13 16:13:33"}, {"id_message": 77614537195, "message": "Yo ya tengo novia xd", "date": "2020-04-13 16:14:39"}, {"id_message": 50699310280, "message": "S S cara llorando de risa cara llorando de risa cara llorando de risa", "date": "2020-04-13 16:15:23"}, {"id_message": 78255834525, "message": "@USER @USER como os habéis unido al grupo ?", "date": "2020-04-13 18:51:53"}, {"id_message": 10446509026, "message": "Una comida típica de Turquía o por ahí", "date": "2020-04-13 18:52:37"}, {"id_message": 34100748013, "message": "En España se vende mucho", "date": "2020-04-13 18:52:59"}, {"id_message": 95043162772, "message": "señal de aprobación con la mano cara llorando de risa", "date": "2020-04-13 18:53:02"}, {"id_message": 61699195711, "message": "Oye , puedo hacerte una pregunta ?", "date": "2020-04-13 18:53:13"}, {"id_message": 85073729018, "message": "Totti no lo habías quitado ?", "date": "2020-04-13 18:53:33"}, {"id_message": 62183615669, "message": "Hay algunos de Argentina", "date": "2020-04-13 18:56:55"}, {"id_message": 12274938707, "message": "cara llorando de risa cara llorando de risa está bien", "date": "2020-04-13 19:09:44"}, {"id_message": 68940422677, "message": "Se nota la edición xd", "date": "2020-04-17 16:21:40"}, {"id_message": 79673672487, "message": "Segunda Colombiana que conozco OuO", "date": "2020-04-17 18:21:52"}, {"id_message": 39599927420, "message": "Yo creo que estudiar medicina es dar bastante", "date": "2020-04-17 18:24:40"}, {"id_message": 10961800521, "message": "Se publican en el momento en el que los uso", "date": "2020-04-17 18:47:00"}, {"id_message": 1063017760, "message": "Claro que sí cara llorando de risa cara llorando de risa", "date": "2020-04-17 18:48:37"}, {"id_message": 71462779997, "message": "Toca sobre el sticker", "date": "2020-04-17 18:48:56"}, {"id_message": 65298416652, "message": "Y le das a \" añadir Stickers \"", "date": "2020-04-17 18:49:16"}, {"id_message": 13929857687, "message": "cara llorando de risa cara llorando de risa señal de aprobación con la mano", "date": "2020-04-17 18:52:18"}, {"id_message": 84735117174, "message": "Es una saga de 7 películas creo", "date": "2020-04-17 19:01:49"}, {"id_message": 46063807436, "message": "Todo chill cara llorando de risa señal de aprobación con la mano palo de corazones", "date": "2020-04-17 19:02:01"}, {"id_message": 62153684547, "message": "Lo encontré y no lo entiendo pero meh", "date": "2020-04-17 19:04:08"}, {"id_message": 65026648431, "message": "@USER estos son los sticker que tengo de gatos", "date": "2020-04-17 19:12:49"}, {"id_message": 26315919779, "message": "Ehhhh Bienvenido de nuevo ! !", "date": "2020-04-18 04:15:36"}, {"id_message": 75475701174, "message": "Para eso no te voy a ayudar", "date": "2020-04-18 04:16:05"}, {"id_message": 60806730540, "message": "Que no nos culpen si al final lo hace ewe", "date": "2020-04-18 17:12:09"}, {"id_message": 61351519073, "message": "Me alegro señal de aprobación con la mano", "date": "2020-04-19 21:32:36"}, {"id_message": 98530455034, "message": "Las del mar por qué tú más no", "date": "2020-04-23 02:30:45"}, {"id_message": 88502592894, "message": "Si ... Alguna vez que me la he mordido", "date": "2020-04-23 02:31:08"}]