[{"id_message": 98731074100, "message": "Soy nueva cara feliz con ojos sonrientes", "date": "2021-10-11 17:11:53"}, {"id_message": 31137391358, "message": "Hace dos días que he salido del área de psiquiatría por intentar suicidarme ... Y no sé muy bien cómo estoy , la verdad", "date": "2021-10-11 17:12:44"}, {"id_message": 64184157842, "message": "Sí , me han puesto tratamiento , pero apenas me levanto de la cama , siento que no estoy haciendo nada", "date": "2021-10-11 17:17:24"}, {"id_message": 83956093570, "message": "Muchas gracias a tod @s ...", "date": "2021-10-11 18:02:25"}, {"id_message": 79184076811, "message": "Buenas noches gente ... estoy volviendo a caer y no se como hacer ... Me quiero hacer daño", "date": "2021-10-11 21:29:37"}, {"id_message": 57327764433, "message": "No ha pasado nada ... Simplemente no puedo más", "date": "2021-10-11 21:32:22"}, {"id_message": 27437723881, "message": "Lo siento si molesto", "date": "2021-10-11 21:32:34"}, {"id_message": 29140923723, "message": "No sé a quien acudir", "date": "2021-10-11 21:32:41"}, {"id_message": 62808252022, "message": "Si , ya lo he tomado pero no se me sale de la cabeza", "date": "2021-10-11 21:35:53"}, {"id_message": 9059626896, "message": "Pues me gustan mucho los perros ... Pasear ... Estudiar", "date": "2021-10-11 21:38:49"}, {"id_message": 34959416826, "message": "Mi trabajo también me gusta , pero ahora estoj de baja ...", "date": "2021-10-11 21:39:09"}, {"id_message": 92587105168, "message": "Si tengo una perra", "date": "2021-10-11 21:39:19"}, {"id_message": 81311874947, "message": "Soy auxiliar de enfermería", "date": "2021-10-11 21:39:36"}, {"id_message": 5256008564, "message": "Es el nombre de un personaje del juego LOL", "date": "2021-10-11 21:40:47"}, {"id_message": 66518504768, "message": "Hace mucho que falta ?", "date": "2021-10-11 21:41:40"}, {"id_message": 11787373686, "message": "Como lo siento ... Pero bueno siempre dejan buenos momentos", "date": "2021-10-11 21:43:05"}, {"id_message": 15935409418, "message": "Creo que la medicación me está haciendo efecto porque me da el sueño ... voy acostarme un poco", "date": "2021-10-11 21:43:55"}, {"id_message": 5753594899, "message": "Muchas gracias por ayudarme", "date": "2021-10-11 21:44:09"}, {"id_message": 88751312544, "message": "Es mezcla de border collie con schnauzer", "date": "2021-10-11 21:44:43"}, {"id_message": 85830578386, "message": "Mil gracias de verdad", "date": "2021-10-11 21:44:55"}, {"id_message": 41309215083, "message": "Si ya me he acostado", "date": "2021-10-11 21:48:00"}, {"id_message": 24348745279, "message": "Hola ... No puedo más ... Me quiero matar ... Ya no veo salida", "date": "2021-10-24 03:26:20"}, {"id_message": 60558518533, "message": "Necesitaba contárselo a alguien", "date": "2021-10-24 03:26:45"}, {"id_message": 68330875237, "message": "No puedo con tanto sufrimiento ya ...", "date": "2021-10-24 03:27:45"}, {"id_message": 67738767921, "message": "He sufrido una violacion hace un año ... Y más pequeñas cosas ... Que van sumando", "date": "2021-10-24 03:28:49"}, {"id_message": 32459645912, "message": "Y yo no puedo más", "date": "2021-10-24 03:28:54"}, {"id_message": 53257119689, "message": "Perdona por las molestias ...", "date": "2021-10-24 03:29:20"}]